Metadata-Version: 2.1
Name: dime-pytorch
Version: 1.0.0
Summary: PyTorch-implementation of the DIME method to detect out-of-distribution observations in deep learning.
Home-page: https://github.com/sartorius-research/dime.pytorch
Author: Rickard Sjoegren
Author-email: rickard.sjoegren@sartorius.com
License: MIT
Platform: UNKNOWN
Classifier: Development Status :: 5 - Production/Stable
Classifier: Programming Language :: Python :: 3
Classifier: Intended Audience :: Science/Research
Classifier: License :: OSI Approved :: MIT License
Classifier: Topic :: Scientific/Engineering :: Artificial Intelligence
Requires-Python: >=3.6
License-File: LICENSE
